setup.cfg
setup.py
sqlQueryTree/__init__.py
sqlQueryTree/sql_query.py
sqlQueryTree.egg-info/PKG-INFO
sqlQueryTree.egg-info/SOURCES.txt
sqlQueryTree.egg-info/dependency_links.txt
sqlQueryTree.egg-info/top_level.txt