Metadata-Version: 2.1
Name: sqlQueryTree
Version: 0.1.1
Summary: building a tree by sql query
Author: VitalBoss28
Author-email: sav4uk_vitaliy28@mail.ru
